MANIFEST.in
README
__init__.py
setup.py
utils.py
data/matrix_r50_c5_rrw.bin
knor/__init__.py
knor/__init__.pyc
knor/knor.cpp
knor.egg-info/PKG-INFO
knor.egg-info/SOURCES.txt
knor.egg-info/dependency_links.txt
knor.egg-info/not-zip-safe
knor.egg-info/requires.txt
knor.egg-info/top_level.txt
knor/Exceptions/__init__.py
knor/Exceptions/runtime.py
knor/cknor/binding/kmeanspp.hpp
knor/cknor/binding/numa_reorg.hpp
knor/cknor/libauto/kmeans.hpp
knor/cknor/libkcommon/AndersonDarling.hpp
knor/cknor/libkcommon/clusters.cpp
knor/cknor/libkcommon/clusters.hpp
knor/cknor/libkcommon/dense_matrix.hpp
knor/cknor/libkcommon/dist_matrix.cpp
knor/cknor/libkcommon/dist_matrix.hpp
knor/cknor/libkcommon/exception.hpp
knor/cknor/libkcommon/hclust_compactor.hpp
knor/cknor/libkcommon/io.cpp
knor/cknor/libkcommon/io.hpp
knor/cknor/libkcommon/kcommon.hpp
knor/cknor/libkcommon/linalg.hpp
knor/cknor/libkcommon/prune_stats.cpp
knor/cknor/libkcommon/prune_stats.hpp
knor/cknor/libkcommon/thd_safe_bool_vector.cpp
knor/cknor/libkcommon/thd_safe_bool_vector.hpp
knor/cknor/libkcommon/thread_state.hpp
knor/cknor/libkcommon/types.cpp
knor/cknor/libkcommon/types.hpp
knor/cknor/libkcommon/util.cpp
knor/cknor/libkcommon/util.hpp
knor/cknor/libman/coordinator.cpp
knor/cknor/libman/coordinator.hpp
knor/cknor/libman/fcm.cpp
knor/cknor/libman/fcm.hpp
knor/cknor/libman/fcm_coordinator.cpp
knor/cknor/libman/fcm_coordinator.hpp
knor/cknor/libman/gmeans.cpp
knor/cknor/libman/gmeans.hpp
knor/cknor/libman/gmeans_coordinator.cpp
knor/cknor/libman/gmeans_coordinator.hpp
knor/cknor/libman/gmm.cpp
knor/cknor/libman/gmm.hpp
knor/cknor/libman/gmm_coordinator.cpp
knor/cknor/libman/gmm_coordinator.hpp
knor/cknor/libman/hclust.cpp
knor/cknor/libman/hclust.hpp
knor/cknor/libman/hclust_coordinator.cpp
knor/cknor/libman/hclust_coordinator.hpp
knor/cknor/libman/hclust_id_generator.hpp
knor/cknor/libman/kmeans_coordinator.cpp
knor/cknor/libman/kmeans_coordinator.hpp
knor/cknor/libman/kmeans_task_coordinator.cpp
knor/cknor/libman/kmeans_task_coordinator.hpp
knor/cknor/libman/kmeans_task_thread.cpp
knor/cknor/libman/kmeans_task_thread.hpp
knor/cknor/libman/kmeans_thread.cpp
