Metadata-Version: 1.0
Name: knor
Version: 0.0.3
Summary: A fast parallel k-means library for Linux and Mac
Home-page: https://github.com/flashxio/knor
Author: Disa Mhembere
Author-email: disa@jhu.edu
License: Apache License, Version 2.0
Keywords: kmeans k-means parallel clustering machine-learning
Platform: UNKNOWN
